karakeep_python_api/__init__.py
karakeep_python_api/__main__.py
karakeep_python_api/datatypes.py
karakeep_python_api/karakeep_api.py
karakeep_python_api/openapi_reference.json
karakeep_python_api-1.4.0.dist-info/licenses/LICENSE
karakeep_python_api-1.4.0.dist-info/METADATA
karakeep_python_api-1.4.0.dist-info/WHEEL
karakeep_python_api-1.4.0.dist-info/entry_points.txt
karakeep_python_api-1.4.0.dist-info/top_level.txt
karakeep_python_api-1.4.0.dist-info/RECORD
