Metadata-Version: 2.4
Name: karakeep_python_api
Version: 1.4.0
Summary: Community python client for the Karakeep API.
Home-page: https://github.com/thiswillbeyourgithub/karakeep_python_api/
License: GPLv3
Keywords: rss,karakeep,hoarder,data-hoarding,python,api,feeds,openapi
Classifier: Programming Language :: Python :: 3
Classifier: License :: OSI Approved :: GNU General Public License v3 (GPLv3)
Classifier: Operating System :: OS Independent
Requires-Python: >=3.9
License-File: LICENSE
Requires-Dist: requests>=2.32.3
Requires-Dist: loguru>=0.7.3
Requires-Dist: pydantic>=2.0
Requires-Dist: click>=8.0
Provides-Extra: dev
Requires-Dist: beartype>=0.20.2; extra == "dev"
Requires-Dist: pytest>=8.3.4; extra == "dev"
Requires-Dist: build>=1.2.2.post1; extra == "dev"
Requires-Dist: twine>=6.1.0; extra == "dev"
Requires-Dist: bumpver>=2024.1130; extra == "dev"
Dynamic: classifier
Dynamic: description
Dynamic: description-content-type
Dynamic: home-page
Dynamic: keywords
Dynamic: license
Dynamic: license-file
Dynamic: provides-extra
Dynamic: requires-dist
Dynamic: requires-python
Dynamic: summary
